{
  "timestamp": 1769240913,
  "timestamp_human": "2026-01-24 10:48:33",
  "cycle_count": 127,
  "bot_status": "running",
  "error_summary": "⚠️ Ошибок: 1 (предупреждений: 1), последняя: 9м назад",
  "error_stats": {
    "total_errors": 1,
    "warnings": 1,
    "errors": 0,
    "critical": 0,
    "recent_errors": [
      "2026-01-24 10:38:54 - WARNING - [CYCLE 125] Still on main, trying again"
    ],
    "last_error_time": 1769240334,
    "error_timestamp_human": "2026-01-24 10:38:54"
  },
  "device_info": {
    "name": "iPhone 7",
    "system_name": "iOS",
    "system_version": "15.8.5",
    "model": "iPhone9,1",
    "identifier_for_vendor": "6C0F4295-99A7-4719-9631-93C305B7606D"
  },
  "battery_info": {
    "battery_state": "2",
    "battery_level": "100",
    "battery_state_string": "Charging",
    "is_charging": true
  },
  "system_stats": {
    "cpu": {
      "load_1": "2.19",
      "load_5": "2.68",
      "load_15": "2.68",
      "cores": 4,
      "utilization_percent": 54.8
    },
    "memory": {
      "total_mb": 2000,
      "used_mb": 238,
      "free_mb": 3,
      "cached_mb": 110,
      "utilization_percent": 11.9
    },
    "disk": {
      "total": "30Gi",
      "used": "7.0Gi",
      "available": "9.0Gi",
      "usage_percent": "44%",
      "mount": "375935"
    },
    "timestamp": 1769240913,
    "timestamp_human": "2026-01-24 10:48:33"
  },
  "last_log": "2026-01-24 10:46:31 - INFO - [CYCLE 126] On main screen\n2026-01-24 10:46:31 - INFO - [CYCLE 126] Step 2/7: Transition to arsenal...\n2026-01-24 10:46:31 - INFO - [CYCLE 126] Quick transition: Кнопка Далее\n2026-01-24 10:46:34 - INFO - [CYCLE 126] Step 3/7: Transition to battle...\n2026-01-24 10:46:34 - INFO - [CYCLE 126] Quick transition: Кнопка Битва\n2026-01-24 10:46:36 - INFO - [CYCLE 126] Step 4/7: Transition to team...\n2026-01-24 10:46:38 - INFO - [CYCLE 126] Waiting for team screen...\n2026-01-24 10:46:39 - INFO - [CYCLE 126] Found attention popup\n2026-01-24 10:46:41 - INFO - [CYCLE 126] Found team screen button\n2026-01-24 10:46:41 - INFO - [CYCLE 126] Step 5/7: Pressing team screen button...\n2026-01-24 10:46:42 - INFO - [CYCLE 126] Step 6/7: Sending invitations...\n2026-01-24 10:46:42 - INFO - [CYCLE 126] Invite #1 sent (0s)\n2026-01-24 10:46:48 - INFO - [CYCLE 126] Invite #2 sent (5s)\n2026-01-24 10:46:54 - INFO - [CYCLE 126] Invite #3 sent (11s)\n2026-01-24 10:47:00 - INFO - [CYCLE 126] Invite #4 sent (17s)\n2026-01-24 10:47:06 - INFO - [CYCLE 126] Invite #5 sent (23s)\n2026-01-24 10:47:12 - DEBUG - [CYCLE 126] Checking for attention popup (invite #5)\n2026-01-24 10:47:12 - INFO - [CYCLE 126] Invite #6 sent (29s)\n2026-01-24 10:47:18 - INFO - [CYCLE 126] Invite #7 sent (35s)\n2026-01-24 10:47:24 - INFO - [CYCLE 126] Invite #8 sent (41s)\n2026-01-24 10:47:30 - INFO - [CYCLE 126] Invite #9 sent (47s)\n2026-01-24 10:47:36 - INFO - [CYCLE 126] Invite #10 sent (53s)\n2026-01-24 10:47:42 - DEBUG - [CYCLE 126] Checking for attention popup (invite #10)\n2026-01-24 10:47:42 - INFO - [CYCLE 126] Invite #11 sent (59s)\n2026-01-24 10:47:43 - INFO - [CYCLE 126] Someone joined immediately!\n2026-01-24 10:47:43 - INFO - [CYCLE 126] Step 7/7: Starting game...\n2026-01-24 10:47:44 - INFO - [CYCLE 126] Checking for loading color at (200, 100)...\n2026-01-24 10:48:10 - INFO - [CYCLE 126] Loading color detected! Color: #A9D917\n2026-01-24 10:48:10 - INFO - [CYCLE 126] Cycle #126 completed successfully - loading color detected\n2026-01-24 10:48:31 - INFO - [CYCLE 126] Connected to ZXTouch\n",
  "update_time": "2026-01-24 10:48:33"
}