{
  "timestamp": 1769259464,
  "timestamp_human": "2026-01-24 15:57:44",
  "cycle_count": 187,
  "bot_status": "running",
  "error_summary": "⚠️ Ошибок: 1 (предупреждений: 1), последняя: 13м назад",
  "error_stats": {
    "total_errors": 1,
    "warnings": 1,
    "errors": 0,
    "critical": 0,
    "recent_errors": [
      "2026-01-24 15:43:51 - WARNING - [CYCLE 183] Still on main, trying again"
    ],
    "last_error_time": 1769258631,
    "error_timestamp_human": "2026-01-24 15:43:51"
  },
  "device_info": {
    "name": "iPhone 7",
    "system_name": "iOS",
    "system_version": "15.8.5",
    "model": "iPhone9,1",
    "identifier_for_vendor": "6C0F4295-99A7-4719-9631-93C305B7606D"
  },
  "battery_info": {
    "battery_state": "2",
    "battery_level": "100",
    "battery_state_string": "Charging",
    "is_charging": true
  },
  "system_stats": {
    "cpu": {
      "load_1": "2.15",
      "load_5": "3.01",
      "load_15": "3.04",
      "cores": 4,
      "utilization_percent": 53.8
    },
    "memory": {
      "total_mb": 2000,
      "used_mb": 239,
      "free_mb": 5,
      "cached_mb": 127,
      "utilization_percent": 11.9
    },
    "disk": {
      "total": "30Gi",
      "used": "7.0Gi",
      "available": "9.0Gi",
      "usage_percent": "44%",
      "mount": "375935"
    },
    "timestamp": 1769259464,
    "timestamp_human": "2026-01-24 15:57:44"
  },
  "last_log": "2026-01-24 15:55:59 - INFO - [CYCLE 186] Waiting for main screen...\n2026-01-24 15:55:59 - DEBUG - [CYCLE 186] Current: unknown, waiting for main... 0s\n2026-01-24 15:56:04 - DEBUG - [CYCLE 186] Current: loading, waiting for main... 5s\n2026-01-24 15:56:05 - DEBUG - [CYCLE 186] Current: loading, waiting for main... 5s\n2026-01-24 15:56:09 - DEBUG - [CYCLE 186] Current: loading, waiting for main... 10s\n2026-01-24 15:56:10 - DEBUG - [CYCLE 186] Current: loading, waiting for main... 10s\n2026-01-24 15:56:14 - DEBUG - [CYCLE 186] Current: loading, waiting for main... 15s\n2026-01-24 15:56:15 - DEBUG - [CYCLE 186] Current: loading, waiting for main... 15s\n2026-01-24 15:56:19 - INFO - [CYCLE 186] On main screen\n2026-01-24 15:56:19 - INFO - [CYCLE 186] Step 2/7: Transition to arsenal...\n2026-01-24 15:56:19 - INFO - [CYCLE 186] Quick transition: Кнопка Далее\n2026-01-24 15:56:22 - INFO - [CYCLE 186] Step 3/7: Transition to battle...\n2026-01-24 15:56:22 - INFO - [CYCLE 186] Quick transition: Кнопка Битва\n2026-01-24 15:56:25 - INFO - [CYCLE 186] Step 4/7: Transition to team...\n2026-01-24 15:56:27 - INFO - [CYCLE 186] Waiting for team screen...\n2026-01-24 15:56:28 - INFO - [CYCLE 186] Found attention popup\n2026-01-24 15:56:29 - INFO - [CYCLE 186] Found team screen button\n2026-01-24 15:56:29 - INFO - [CYCLE 186] Step 5/7: Pressing team screen button...\n2026-01-24 15:56:31 - INFO - [CYCLE 186] Step 6/7: Sending invitations...\n2026-01-24 15:56:31 - INFO - [CYCLE 186] Invite #1 sent (0s)\n2026-01-24 15:56:37 - INFO - [CYCLE 186] Invite #2 sent (6s)\n2026-01-24 15:56:43 - INFO - [CYCLE 186] Invite #3 sent (12s)\n2026-01-24 15:56:49 - INFO - [CYCLE 186] Invite #4 sent (17s)\n2026-01-24 15:56:54 - INFO - [CYCLE 186] Invite #5 sent (23s)\n2026-01-24 15:56:55 - INFO - [CYCLE 186] Someone joined immediately!\n2026-01-24 15:56:55 - INFO - [CYCLE 186] Step 7/7: Starting game...\n2026-01-24 15:56:57 - INFO - [CYCLE 186] Checking for loading color at (200, 100)...\n2026-01-24 15:57:21 - INFO - [CYCLE 186] Loading color detected! Color: #A9D917\n2026-01-24 15:57:21 - INFO - [CYCLE 186] Cycle #186 completed successfully - loading color detected\n2026-01-24 15:57:42 - INFO - [CYCLE 186] Connected to ZXTouch\n",
  "update_time": "2026-01-24 15:57:44"
}