{
  "timestamp": 1768832969,
  "timestamp_human": "2026-01-19 17:29:29",
  "cycle_count": 319,
  "bot_status": "running",
  "error_summary": "⚠️ Ошибок: 62 (предупреждений: 31, ошибок: 31), последняя: 23с назад",
  "error_stats": {
    "total_errors": 62,
    "warnings": 31,
    "errors": 31,
    "critical": 0,
    "recent_errors": [
      "2026-01-19 17:25:15 - ERROR - [CYCLE 316] Main screen not found",
      "2026-01-19 17:27:10 - WARNING - [CYCLE 317] Failed to reach main screen",
      "2026-01-19 17:27:10 - ERROR - [CYCLE 317] Main screen not found",
      "2026-01-19 17:29:06 - WARNING - [CYCLE 318] Failed to reach main screen",
      "2026-01-19 17:29:06 - ERROR - [CYCLE 318] Main screen not found"
    ],
    "last_error_time": 1768832946,
    "error_timestamp_human": "2026-01-19 17:29:06"
  },
  "device_info": {
    "name": "iPhone 7",
    "system_name": "iOS",
    "system_version": "15.8.5",
    "model": "iPhone9,1",
    "identifier_for_vendor": "6C0F4295-99A7-4719-9631-93C305B7606D"
  },
  "battery_info": {
    "battery_state": "2",
    "battery_level": "100",
    "battery_state_string": "Charging",
    "is_charging": true
  },
  "system_stats": {
    "cpu": {
      "load_1": "4.00",
      "load_5": "4.64",
      "load_15": "5.33",
      "cores": 4,
      "utilization_percent": 100.0
    },
    "memory": {
      "total_mb": 2000,
      "used_mb": 232,
      "free_mb": 2,
      "cached_mb": 127,
      "utilization_percent": 11.6
    },
    "disk": {
      "total": "30Gi",
      "used": "7.0Gi",
      "available": "9.5Gi",
      "usage_percent": "43%",
      "mount": "375935"
    },
    "timestamp": 1768832969,
    "timestamp_human": "2026-01-19 17:29:29"
  },
  "last_log": "2026-01-19 17:27:36 - DEBUG - [CYCLE 318] Current: unknown, waiting for main... 0s\n2026-01-19 17:27:36 - DEBUG - [CYCLE 318] Current: unknown, waiting for main... 0s\n2026-01-19 17:27:41 - DEBUG - [CYCLE 318] Current: unknown, waiting for main... 5s\n2026-01-19 17:27:46 - DEBUG - [CYCLE 318] Current: unknown, waiting for main... 10s\n2026-01-19 17:27:46 - DEBUG - [CYCLE 318] Current: unknown, waiting for main... 10s\n2026-01-19 17:27:51 - DEBUG - [CYCLE 318] Current: unknown, waiting for main... 15s\n2026-01-19 17:27:51 - DEBUG - [CYCLE 318] Current: unknown, waiting for main... 15s\n2026-01-19 17:27:56 - DEBUG - [CYCLE 318] Current: unknown, waiting for main... 20s\n2026-01-19 17:28:01 - DEBUG - [CYCLE 318] Current: unknown, waiting for main... 25s\n2026-01-19 17:28:01 - DEBUG - [CYCLE 318] Current: unknown, waiting for main... 25s\n2026-01-19 17:28:06 - DEBUG - [CYCLE 318] Current: unknown, waiting for main... 30s\n2026-01-19 17:28:06 - DEBUG - [CYCLE 318] Current: unknown, waiting for main... 30s\n2026-01-19 17:28:11 - DEBUG - [CYCLE 318] Current: unknown, waiting for main... 35s\n2026-01-19 17:28:16 - DEBUG - [CYCLE 318] Current: unknown, waiting for main... 40s\n2026-01-19 17:28:21 - DEBUG - [CYCLE 318] Current: unknown, waiting for main... 45s\n2026-01-19 17:28:26 - DEBUG - [CYCLE 318] Current: unknown, waiting for main... 50s\n2026-01-19 17:28:31 - DEBUG - [CYCLE 318] Current: unknown, waiting for main... 55s\n2026-01-19 17:28:36 - DEBUG - [CYCLE 318] Current: unknown, waiting for main... 60s\n2026-01-19 17:28:41 - DEBUG - [CYCLE 318] Current: unknown, waiting for main... 65s\n2026-01-19 17:28:41 - DEBUG - [CYCLE 318] Current: unknown, waiting for main... 65s\n2026-01-19 17:28:46 - DEBUG - [CYCLE 318] Current: unknown, waiting for main... 70s\n2026-01-19 17:28:46 - DEBUG - [CYCLE 318] Current: unknown, waiting for main... 70s\n2026-01-19 17:28:51 - DEBUG - [CYCLE 318] Current: unknown, waiting for main... 75s\n2026-01-19 17:28:51 - DEBUG - [CYCLE 318] Current: unknown, waiting for main... 75s\n2026-01-19 17:28:56 - DEBUG - [CYCLE 318] Current: unknown, waiting for main... 80s\n2026-01-19 17:28:56 - DEBUG - [CYCLE 318] Current: unknown, waiting for main... 80s\n2026-01-19 17:29:01 - DEBUG - [CYCLE 318] Current: unknown, waiting for main... 85s\n2026-01-19 17:29:06 - WARNING - [CYCLE 318] Failed to reach main screen\n2026-01-19 17:29:06 - ERROR - [CYCLE 318] Main screen not found\n2026-01-19 17:29:26 - INFO - [CYCLE 318] Connected to ZXTouch\n",
  "update_time": "2026-01-19 17:29:29"
}