{
  "timestamp": 1770274038,
  "timestamp_human": "2026-02-05 09:47:18",
  "cycle_count": 11,
  "bot_status": "running",
  "error_summary": "⚠️ Ошибок: 39 (предупреждений: 18, ошибок: 19, критических: 2), последняя: 23с назад",
  "error_stats": {
    "total_errors": 39,
    "warnings": 18,
    "errors": 19,
    "critical": 2,
    "recent_errors": [
      "2026-02-05 09:42:59 - ERROR - [CYCLE 8] Main screen not found",
      "2026-02-05 09:44:57 - WARNING - [CYCLE 9] Failed to reach main screen",
      "2026-02-05 09:44:57 - ERROR - [CYCLE 9] Main screen not found",
      "2026-02-05 09:46:55 - WARNING - [CYCLE 10] Failed to reach main screen",
      "2026-02-05 09:46:55 - ERROR - [CYCLE 10] Main screen not found"
    ],
    "last_error_time": 1770274015,
    "error_timestamp_human": "2026-02-05 09:46:55"
  },
  "device_info": {
    "name": "iPhone 7",
    "system_name": "iOS",
    "system_version": "15.8.5",
    "model": "iPhone9,1",
    "identifier_for_vendor": "6C0F4295-99A7-4719-9631-93C305B7606D"
  },
  "battery_info": {
    "battery_state": "2",
    "battery_level": "100",
    "battery_state_string": "Charging",
    "is_charging": true
  },
  "system_stats": {
    "cpu": {
      "load_1": "3.17",
      "load_5": "2.05",
      "load_15": "2.00",
      "cores": 4,
      "utilization_percent": 79.2
    },
    "memory": {
      "total_mb": 2000,
      "used_mb": 242,
      "free_mb": 5,
      "cached_mb": 144,
      "utilization_percent": 12.1
    },
    "disk": {
      "total": "30Gi",
      "used": "7.0Gi",
      "available": "9.0Gi",
      "usage_percent": "44%",
      "mount": "376219"
    },
    "timestamp": 1770274038,
    "timestamp_human": "2026-02-05 09:47:18"
  },
  "last_log": "2026-02-05 09:46:07 - INFO - [CYCLE 10] Found ВНИМАНИЕ popup\n2026-02-05 09:46:09 - INFO - [CYCLE 10] Found ВНИМАНИЕ popup\n2026-02-05 09:46:11 - INFO - [CYCLE 10] Found ВНИМАНИЕ popup\n2026-02-05 09:46:12 - INFO - [CYCLE 10] Found ВНИМАНИЕ popup\n2026-02-05 09:46:15 - INFO - [CYCLE 10] Found ВНИМАНИЕ popup\n2026-02-05 09:46:16 - INFO - [CYCLE 10] Found ВНИМАНИЕ popup\n2026-02-05 09:46:18 - DEBUG - [CYCLE 10] Current: popup, waiting for main... 55s\n2026-02-05 09:46:18 - INFO - [CYCLE 10] Found ВНИМАНИЕ popup\n2026-02-05 09:46:20 - INFO - [CYCLE 10] Found ВНИМАНИЕ popup\n2026-02-05 09:46:22 - INFO - [CYCLE 10] Found ВНИМАНИЕ popup\n2026-02-05 09:46:23 - INFO - [CYCLE 10] Found ВНИМАНИЕ popup\n2026-02-05 09:46:26 - INFO - [CYCLE 10] Found ВНИМАНИЕ popup\n2026-02-05 09:46:27 - INFO - [CYCLE 10] Found ВНИМАНИЕ popup\n2026-02-05 09:46:29 - INFO - [CYCLE 10] Found ВНИМАНИЕ popup\n2026-02-05 09:46:31 - INFO - [CYCLE 10] Found ВНИМАНИЕ popup\n2026-02-05 09:46:33 - INFO - [CYCLE 10] Found ВНИМАНИЕ popup\n2026-02-05 09:46:35 - INFO - [CYCLE 10] Found ВНИМАНИЕ popup\n2026-02-05 09:46:37 - INFO - [CYCLE 10] Found ВНИМАНИЕ popup\n2026-02-05 09:46:38 - INFO - [CYCLE 10] Found ВНИМАНИЕ popup\n2026-02-05 09:46:40 - INFO - [CYCLE 10] Found ВНИМАНИЕ popup\n2026-02-05 09:46:42 - INFO - [CYCLE 10] Found ВНИМАНИЕ popup\n2026-02-05 09:46:44 - INFO - [CYCLE 10] Found ВНИМАНИЕ popup\n2026-02-05 09:46:46 - INFO - [CYCLE 10] Found ВНИМАНИЕ popup\n2026-02-05 09:46:48 - INFO - [CYCLE 10] Found ВНИМАНИЕ popup\n2026-02-05 09:46:49 - INFO - [CYCLE 10] Found ВНИМАНИЕ popup\n2026-02-05 09:46:51 - INFO - [CYCLE 10] Found ВНИМАНИЕ popup\n2026-02-05 09:46:53 - INFO - [CYCLE 10] Found ВНИМАНИЕ popup\n2026-02-05 09:46:55 - WARNING - [CYCLE 10] Failed to reach main screen\n2026-02-05 09:46:55 - ERROR - [CYCLE 10] Main screen not found\n2026-02-05 09:47:16 - INFO - [CYCLE 10] Connected to ZXTouch\n",
  "update_time": "2026-02-05 09:47:18"
}