{
  "timestamp": 1770116914,
  "timestamp_human": "2026-02-03 14:08:34",
  "cycle_count": 6,
  "bot_status": "running",
  "error_summary": "⚠️ Ошибок: 1 (предупреждений: 1), последняя: 3ч назад",
  "error_stats": {
    "total_errors": 1,
    "warnings": 1,
    "errors": 0,
    "critical": 0,
    "recent_errors": [
      "2026-02-03 10:45:45 - WARNING - [CYCLE 489] Still on main, trying again"
    ],
    "last_error_time": 1770104745,
    "error_timestamp_human": "2026-02-03 10:45:45"
  },
  "device_info": {
    "name": "iPhone 7",
    "system_name": "iOS",
    "system_version": "15.8.5",
    "model": "iPhone9,1",
    "identifier_for_vendor": "6C0F4295-99A7-4719-9631-93C305B7606D"
  },
  "battery_info": {
    "battery_state": "2",
    "battery_level": "100",
    "battery_state_string": "Charging",
    "is_charging": true
  },
  "system_stats": {
    "cpu": {
      "load_1": "2.11",
      "load_5": "1.81",
      "load_15": "1.80",
      "cores": 4,
      "utilization_percent": 52.8
    },
    "memory": {
      "total_mb": 2000,
      "used_mb": 234,
      "free_mb": 6,
      "cached_mb": 131,
      "utilization_percent": 11.7
    },
    "disk": {
      "total": "30Gi",
      "used": "7.0Gi",
      "available": "9.2Gi",
      "usage_percent": "44%",
      "mount": "376219"
    },
    "timestamp": 1770116914,
    "timestamp_human": "2026-02-03 14:08:34"
  },
  "last_log": "2026-02-03 14:05:47 - INFO - [CYCLE 5] Invite #21 sent (118s)\n2026-02-03 14:05:53 - INFO - [CYCLE 5] Invite #22 sent (123s)\n2026-02-03 14:05:59 - INFO - [CYCLE 5] Invite #23 sent (129s)\n2026-02-03 14:06:05 - INFO - [CYCLE 5] Invite #24 sent (135s)\n2026-02-03 14:06:11 - INFO - [CYCLE 5] Invite #25 sent (141s)\n2026-02-03 14:06:16 - DEBUG - [CYCLE 5] Checking for attention popup (invite #25)\n2026-02-03 14:06:17 - INFO - [CYCLE 5] Invite #26 sent (147s)\n2026-02-03 14:06:23 - INFO - [CYCLE 5] Invite #27 sent (153s)\n2026-02-03 14:06:28 - INFO - [CYCLE 5] Invite #28 sent (159s)\n2026-02-03 14:06:34 - INFO - [CYCLE 5] Invite #29 sent (165s)\n2026-02-03 14:06:40 - INFO - [CYCLE 5] Invite #30 sent (171s)\n2026-02-03 14:06:46 - DEBUG - [CYCLE 5] Checking for attention popup (invite #30)\n2026-02-03 14:06:46 - INFO - [CYCLE 5] Invite #31 sent (177s)\n2026-02-03 14:06:52 - INFO - [CYCLE 5] Invite #32 sent (183s)\n2026-02-03 14:06:58 - INFO - [CYCLE 5] Invite #33 sent (188s)\n2026-02-03 14:07:04 - INFO - [CYCLE 5] Invite #34 sent (194s)\n2026-02-03 14:07:10 - INFO - [CYCLE 5] Invite #35 sent (200s)\n2026-02-03 14:07:16 - DEBUG - [CYCLE 5] Checking for attention popup (invite #35)\n2026-02-03 14:07:16 - INFO - [CYCLE 5] Invite #36 sent (206s)\n2026-02-03 14:07:22 - INFO - [CYCLE 5] Invite #37 sent (212s)\n2026-02-03 14:07:27 - INFO - [CYCLE 5] Invite #38 sent (218s)\n2026-02-03 14:07:33 - INFO - [CYCLE 5] Invite #39 sent (224s)\n2026-02-03 14:07:39 - INFO - [CYCLE 5] Invite #40 sent (230s)\n2026-02-03 14:07:45 - DEBUG - [CYCLE 5] Checking for attention popup (invite #40)\n2026-02-03 14:07:45 - INFO - [CYCLE 5] Someone joined the team!\n2026-02-03 14:07:45 - INFO - [CYCLE 5] Step 7/7: Starting game...\n2026-02-03 14:07:47 - INFO - [CYCLE 5] Checking for loading color at (200, 100)...\n2026-02-03 14:08:11 - INFO - [CYCLE 5] Loading color detected! Color: #A9D917\n2026-02-03 14:08:11 - INFO - [CYCLE 5] Cycle #5 completed successfully - loading color detected\n2026-02-03 14:08:32 - INFO - [CYCLE 5] Connected to ZXTouch\n",
  "update_time": "2026-02-03 14:08:34"
}