{
  "timestamp": 1768742638,
  "timestamp_human": "2026-01-18 16:23:58",
  "cycle_count": 483,
  "bot_status": "running",
  "error_summary": "⚠️ Ошибок: 1 (предупреждений: 1), последняя: 57м назад",
  "error_stats": {
    "total_errors": 1,
    "warnings": 1,
    "errors": 0,
    "critical": 0,
    "recent_errors": [
      "2026-01-18 15:26:25 - WARNING - [CYCLE 470] Still on main, trying again"
    ],
    "last_error_time": 1768739185,
    "error_timestamp_human": "2026-01-18 15:26:25"
  },
  "device_info": {
    "name": "iPhone 7",
    "system_name": "iOS",
    "system_version": "15.8.5",
    "model": "iPhone9,1",
    "identifier_for_vendor": "6C0F4295-99A7-4719-9631-93C305B7606D"
  },
  "battery_info": {
    "battery_state": "2",
    "battery_level": "100",
    "battery_state_string": "Charging",
    "is_charging": true
  },
  "system_stats": {
    "cpu": {
      "load_1": "1.84",
      "load_5": "2.26",
      "load_15": "2.56",
      "cores": 4,
      "utilization_percent": 46.0
    },
    "memory": {
      "total_mb": 2000,
      "used_mb": 238,
      "free_mb": 4,
      "cached_mb": 99,
      "utilization_percent": 11.9
    },
    "disk": {
      "total": "30Gi",
      "used": "7.0Gi",
      "available": "9.5Gi",
      "usage_percent": "43%",
      "mount": "375935"
    },
    "timestamp": 1768742638,
    "timestamp_human": "2026-01-18 16:23:58"
  },
  "last_log": "2026-01-18 16:21:12 - INFO - [CYCLE 482] Invite #27 sent (153s)\n2026-01-18 16:21:18 - INFO - [CYCLE 482] Invite #28 sent (159s)\n2026-01-18 16:21:23 - INFO - [CYCLE 482] Invite #29 sent (165s)\n2026-01-18 16:21:29 - INFO - [CYCLE 482] Invite #30 sent (170s)\n2026-01-18 16:21:35 - DEBUG - [CYCLE 482] Checking for attention popup (invite #30)\n2026-01-18 16:21:35 - INFO - [CYCLE 482] Invite #31 sent (176s)\n2026-01-18 16:21:41 - INFO - [CYCLE 482] Invite #32 sent (182s)\n2026-01-18 16:21:47 - INFO - [CYCLE 482] Invite #33 sent (188s)\n2026-01-18 16:21:53 - INFO - [CYCLE 482] Invite #34 sent (194s)\n2026-01-18 16:21:59 - INFO - [CYCLE 482] Invite #35 sent (200s)\n2026-01-18 16:22:05 - DEBUG - [CYCLE 482] Checking for attention popup (invite #35)\n2026-01-18 16:22:05 - INFO - [CYCLE 482] Invite #36 sent (206s)\n2026-01-18 16:22:11 - INFO - [CYCLE 482] Invite #37 sent (212s)\n2026-01-18 16:22:17 - INFO - [CYCLE 482] Invite #38 sent (218s)\n2026-01-18 16:22:22 - INFO - [CYCLE 482] Invite #39 sent (224s)\n2026-01-18 16:22:28 - INFO - [CYCLE 482] Invite #40 sent (229s)\n2026-01-18 16:22:34 - DEBUG - [CYCLE 482] Checking for attention popup (invite #40)\n2026-01-18 16:22:34 - INFO - [CYCLE 482] Invite #41 sent (235s)\n2026-01-18 16:22:40 - INFO - [CYCLE 482] Invite #42 sent (241s)\n2026-01-18 16:22:46 - INFO - [CYCLE 482] Invite #43 sent (247s)\n2026-01-18 16:22:52 - INFO - [CYCLE 482] Invite #44 sent (253s)\n2026-01-18 16:22:58 - INFO - [CYCLE 482] Invite #45 sent (259s)\n2026-01-18 16:23:04 - DEBUG - [CYCLE 482] Checking for attention popup (invite #45)\n2026-01-18 16:23:04 - INFO - [CYCLE 482] Invite #46 sent (265s)\n2026-01-18 16:23:10 - INFO - [CYCLE 482] Someone joined the team!\n2026-01-18 16:23:10 - INFO - [CYCLE 482] Step 7/7: Starting game...\n2026-01-18 16:23:11 - INFO - [CYCLE 482] Checking for loading color at (200, 100)...\n2026-01-18 16:23:35 - INFO - [CYCLE 482] Loading color detected! Color: #A9D917\n2026-01-18 16:23:35 - INFO - [CYCLE 482] Cycle #482 completed successfully - loading color detected\n2026-01-18 16:23:56 - INFO - [CYCLE 482] Connected to ZXTouch\n",
  "update_time": "2026-01-18 16:23:58"
}